pubsub.py
py_ipfs_pubsub-0.0.2.dist-info/LICENSE
py_ipfs_pubsub-0.0.2.dist-info/METADATA
py_ipfs_pubsub-0.0.2.dist-info/WHEEL
py_ipfs_pubsub-0.0.2.dist-info/top_level.txt
py_ipfs_pubsub-0.0.2.dist-info/RECORD
