Metadata-Version: 2.1
Name: py-ipfs-pubsub
Version: 0.0.2
Summary: Pubsub client for python, since ipfshttpclient pubsub isn't compatibe with the newer versions of ipfs
Author: @ZachisGit
Classifier: Programming Language :: Python :: 3
Classifier: License :: OSI Approved :: MIT License
Classifier: Operating System :: OS Independent
Requires-Python: >=3.6
License-File: LICENSE
Requires-Dist: requests (>=2.23.0)
Requires-Dist: py-multibase (>=1.0.3)
